yadopt/__init__.py
yadopt/argopt.py
yadopt/argvec.py
yadopt/checker.py
yadopt/color.py
yadopt/dtypes.py
yadopt/errors.py
yadopt/gendat.py
yadopt/hints.py
yadopt/matchers.py
yadopt/persist.py
yadopt/toml.py
yadopt/usage.py
yadopt/utils.py
yadopt/yadopt.py
yadopt-2026.1.5.dist-info/METADATA
yadopt-2026.1.5.dist-info/WHEEL
yadopt-2026.1.5.dist-info/licenses/LICENSE
yadopt-2026.1.5.dist-info/RECORD
