Metadata-Version: 2.4
Name: yadopt
Version: 2026.1.5
Summary: Yet another docopt, a human-friendly command line arguments parser.
Project-URL: Repository, https://github.com/tiskw/yadopt
Project-URL: Issues, https://github.com/tiskw/yadopt/issues
Author-email: Tetsuya Ishikawa <tiskw111@gmail.com>
License: MIT License
License-File: LICENSE
Classifier: Development Status :: 4 - Beta
Classifier: Intended Audience :: Developers
Classifier: License :: OSI Approved :: MIT License
Classifier: Operating System :: OS Independent
Classifier: Programming Language :: Python :: 3
Requires-Python: >=3.10
Requires-Dist: tomli; python_version <= '3.10'
